ethiocalendar/__init__.py
ethiocalendar/ethiocalendar.py
ethiocalendar-1.0.2.dist-info/LICENSE.txt
ethiocalendar-1.0.2.dist-info/METADATA
ethiocalendar-1.0.2.dist-info/WHEEL
ethiocalendar-1.0.2.dist-info/top_level.txt
ethiocalendar-1.0.2.dist-info/RECORD
