Metadata-Version: 2.1
Name: ethiocalendar
Version: 1.0.2
Summary: Ethiopian Calendar based date and time module
Home-page: https://github.com/mukerem/ethiocalendar
Download-URL: https://github.com/mukerem/ethiocalendar/archive/refs/tags/v1.1.tar.gz
Author: Mukerem Ali
Author-email: mukeremali112@gmail.com
License: MIT
Classifier: Development Status :: 3 - Alpha
Classifier: Intended Audience :: Developers
Classifier: Topic :: Software Development :: Build Tools
Classifier: License :: OSI Approved :: MIT License
Classifier: Programming Language :: Python :: 2.7
Classifier: Programming Language :: Python :: 3
Classifier: Programming Language :: Python :: 3.3
Classifier: Programming Language :: Python :: 3.4
Classifier: Programming Language :: Python :: 3.5
Classifier: Programming Language :: Python :: 3.6
Classifier: Programming Language :: Python :: 3.7
Classifier: Programming Language :: Python :: 3.8
Classifier: Programming Language :: Python :: 3.9
Classifier: Programming Language :: Python :: 3.10
Classifier: Programming Language :: Python :: 3.11
License-File: LICENSE.txt
